mikatools/__init__.py
mikatools/cache.py
mikatools/crypto.py
mikatools/fix_certs.py
mikatools/mt.py
mikatools-1.0.1.dist-info/LICENSE
mikatools-1.0.1.dist-info/METADATA
mikatools-1.0.1.dist-info/WHEEL
mikatools-1.0.1.dist-info/top_level.txt
mikatools-1.0.1.dist-info/RECORD
