Metadata-Version: 2.1
Name: mikatools
Version: 1.0.1
Summary: Quick methods for everyday Python programming
Home-page: https://github.com/mikahama/mikatools
Author: Mika Hämäläinen
Author-email: mika.hamalainen@helsinki.fi
Classifier: Programming Language :: Python :: 3
Classifier: License :: OSI Approved :: MIT License
Classifier: Operating System :: OS Independent
License-File: LICENSE
Requires-Dist: requests
Requires-Dist: tqdm
Requires-Dist: cryptography
